{
  "providers": {
    "awscloudformation": {
      "AuthRoleName": "amplify-knightmarket-dev-7623e-authRole",
      "UnauthRoleArn": "arn:aws:iam::147997151910:role/amplify-knightmarket-dev-7623e-unauthRole",
      "AuthRoleArn": "arn:aws:iam::147997151910:role/amplify-knightmarket-dev-7623e-authRole",
      "Region": "us-east-2",
      "DeploymentBucketName": "amplify-knightmarket-dev-7623e-deployment",
      "UnauthRoleName": "amplify-knightmarket-dev-7623e-unauthRole",
      "StackName": "amplify-knightmarket-dev-7623e",
      "StackId": "arn:aws:cloudformation:us-east-2:147997151910:stack/amplify-knightmarket-dev-7623e/b9b2b2f0-b5bc-11ef-8d98-0a67eb8ecf7b",
      "AmplifyAppId": "d34yoa95di7wqw"
    }
  },
  "auth": {
    "knightmarketf0bc4d5d": {
      "service": "Cognito",
      "providerPlugin": "awscloudformation",
      "dependsOn": [],
      "customAuth": false,
      "frontendAuthConfig": {
        "socialProviders": [],
        "usernameAttributes": [],
        "signupAttributes": [
          "EMAIL"
        ],
        "passwordProtectionSettings": {
          "passwordPolicyMinLength": 8,
          "passwordPolicyCharacters": []
        },
        "mfaConfiguration": "OFF",
        "mfaTypes": [
          "SMS"
        ],
        "verificationMechanisms": [
          "EMAIL"
        ]
      },
      "providerMetadata": {
        "s3TemplateURL": "https://s3.amazonaws.com/amplify-knightmarket-dev-7623e-deployment/amplify-cfn-templates/auth/knightmarketf0bc4d5d-cloudformation-template.json",
        "logicalId": "authknightmarketf0bc4d5d"
      },
      "lastPushTimeStamp": "2024-12-08T23:36:42.615Z",
      "output": {
        "UserPoolId": "us-east-2_LYZqn4wVX",
        "AppClientIDWeb": "1chovla1u6h02tntqskp367f1b",
        "AppClientID": "6a97ffpu9pl8emdam64qt304ns",
        "IdentityPoolId": "us-east-2:12c69cba-7e32-4c40-996f-de29f178dc6d",
        "UserPoolArn": "arn:aws:cognito-idp:us-east-2:147997151910:userpool/us-east-2_LYZqn4wVX",
        "IdentityPoolName": "knightmarketf0bc4d5d_identitypool_f0bc4d5d__dev",
        "UserPoolName": "knightmarketf0bc4d5d_userpool_f0bc4d5d"
      },
      "lastPushDirHash": "9U8YyC6XTvWLaqGlqXGt5zz3oHk="
    }
  }
}